dsp_toolkit/__init__.py
dsp_toolkit/filtering/__init__.py
dsp_toolkit/filtering/filters.py
dsp_toolkit/filtering/xia_filters.py
dsp_toolkit/sample_data/__init__.py
dsp_toolkit/sample_data/sample_energy_spectra.py
dsp_toolkit/sample_data/sample_traces.py
dsp_toolkit/signal_pileup/__init__.py
dsp_toolkit/signal_pileup/pileup.py
dsp_toolkit/timing/__init__.py
dsp_toolkit/timing/constant_fraction_discriminators.py
dsp_toolkit/timing/fitters.py
dsp_toolkit-2.8.2.dist-info/LICENSE
dsp_toolkit-2.8.2.dist-info/METADATA
dsp_toolkit-2.8.2.dist-info/WHEEL
dsp_toolkit-2.8.2.dist-info/top_level.txt
dsp_toolkit-2.8.2.dist-info/RECORD
