Metadata-Version: 2.1
Name: dsp-toolkit
Version: 2.8.2
Summary: Functions useful for analyzing digitized signals.
Home-page: https://github.com/spaulaus/dsp_toolkit
Author: S. V. Paulauskas
Author-email: stanpaulauskas@gmail.com
License: Apache License Version 2.0
Platform: UNKNOWN
Classifier: Development Status :: 4 - Beta
Classifier: Intended Audience :: Science/Research
Classifier: Programming Language :: Python :: 3
Classifier: Programming Language :: Python :: 3 :: Only
Classifier: License :: OSI Approved :: Apache Software License
Classifier: Topic :: Scientific/Engineering :: Physics
Classifier: Operating System :: OS Independent
Requires-Dist: numpy
Requires-Dist: scipy
